LICENSE.txt
MANIFEST.in
README.rst
setup.py
django_scripts_tracker/__init__.py
django_scripts_tracker/apps.py
django_scripts_tracker/core_tracker.py
django_scripts_tracker/dependency_resolver.py
django_scripts_tracker/dependency_tracker.py
django_scripts_tracker/git_plugin.py
django_scripts_tracker/models.py
django_scripts_tracker/settings.py
django_scripts_tracker/tests.py
django_scripts_tracker/tracker_commons.py
django_scripts_tracker/utils.py
django_scripts_tracker.egg-info/PKG-INFO
django_scripts_tracker.egg-info/SOURCES.txt
django_scripts_tracker.egg-info/dependency_links.txt
django_scripts_tracker.egg-info/top_level.txt
django_scripts_tracker/management/__init__.py
django_scripts_tracker/management/commands/__init__.py
django_scripts_tracker/management/commands/check_scripts.py
django_scripts_tracker/management/commands/run_all_scripts.py
django_scripts_tracker/migrations/0001_initial.py
django_scripts_tracker/migrations/__init__.py
docs/_config.yml
docs/index.md