Metadata-Version: 1.1
Name: django-scripts-tracker
Version: 0.2
Summary: An unofficial Django utility tool that tracks management scripts execution
Home-page: https://krzysiek555.github.io/django-scripts-tracker/
Author: Krzysztof Falcman
Author-email: dev@krzysiekf.cba.pl
License: MIT License
Platform: UNKNOWN
Classifier: Environment :: Web Environment
Classifier: Framework :: Django
Classifier: Framework :: Django :: 1.11
Classifier: Intended Audience :: Developers
Classifier: License :: OSI Approved :: MIT License
Classifier: Operating System :: OS Independent
Classifier: Programming Language :: Python
Classifier: Programming Language :: Python :: 2.7
Classifier: Programming Language :: Python :: 3.6
Classifier: Topic :: Software Development
